intuitiveml/Information.py
intuitiveml/__init__.py
intuitiveml/utils.py
intuitiveml/algebra/Dimensions.py
intuitiveml/algebra/LinearAlgebra.py
intuitiveml/algebra/Norm.py
intuitiveml/algebra/__init__.py
intuitiveml/feature/PCA.py
intuitiveml/feature/Scaling.py
intuitiveml/feature/__init__.py
intuitiveml/optimizer/GradientDescent.py
intuitiveml/optimizer/__init__.py
intuitiveml/supervised/__init__.py
intuitiveml/supervised/classification/Activations.py
intuitiveml/supervised/classification/DecisionTree.py
intuitiveml/supervised/classification/KNN.py
intuitiveml/supervised/classification/LogisticRegression.py
intuitiveml/supervised/classification/RandomForest.py
intuitiveml/supervised/classification/SVM.py
intuitiveml/supervised/classification/__init__.py
intuitiveml/supervised/regression/BiasVariance.py
intuitiveml/supervised/regression/GradientBoostedTrees.py
intuitiveml/supervised/regression/LinearRegression.py
intuitiveml/supervised/regression/RegularizedRegression.py
intuitiveml/supervised/regression/__init__.py
intuitiveml/unsupervised/KMeans.py
intuitiveml/unsupervised/__init__.py
intuitiveml-0.0.1a3.dist-info/DESCRIPTION.rst
intuitiveml-0.0.1a3.dist-info/METADATA
intuitiveml-0.0.1a3.dist-info/RECORD
intuitiveml-0.0.1a3.dist-info/WHEEL
intuitiveml-0.0.1a3.dist-info/metadata.json
intuitiveml-0.0.1a3.dist-info/top_level.txt
