Metadata-Version: 2.0
Name: intuitiveml
Version: 0.0.1a3
Summary: Intuitive ML
Home-page: UNKNOWN
Author: Daniel Voigt Godoy
Author-email: datagnosis@gmail.com
License: MIT
Keywords: machine learning,algorithms,visualization,interactive
Platform: UNKNOWN
Classifier: Development Status :: 3 - Alpha
Classifier: Intended Audience :: Developers
Classifier: Intended Audience :: Education
Classifier: Intended Audience :: Science/Research
Classifier: Topic :: Scientific/Engineering
Classifier: Topic :: Scientific/Engineering :: Artificial Intelligence
Classifier: Topic :: Scientific/Engineering :: Visualization
Classifier: Topic :: System :: Distributed Computing
Classifier: License :: OSI Approved :: MIT License
Classifier: Programming Language :: Python :: 3
Requires-Dist: numpy
Requires-Dist: scipy
Requires-Dist: pandas
Requires-Dist: scikit-learn
Requires-Dist: plotly
Requires-Dist: ipywidgets
Requires-Dist: deepreplay
